gherkin/__init__.py
gherkin/ast_builder.py
gherkin/ast_node.py
gherkin/dialect.py
gherkin/errors.py
gherkin/gherkin-languages.json
gherkin/gherkin_line.py
gherkin/parser.py
gherkin/parser_types.py
gherkin/pickles/__init__.py
gherkin/pickles/compiler.py
gherkin/py.typed
gherkin/stream/__init__.py
gherkin/stream/gherkin_events.py
gherkin/stream/id_generator.py
gherkin/stream/source_events.py
gherkin/token.py
gherkin/token_formatter_builder.py
gherkin/token_matcher.py
gherkin/token_matcher_markdown.py
gherkin/token_scanner.py
gherkin_official-38.0.0.dist-info/licenses/LICENSE
gherkin_official-38.0.0.dist-info/WHEEL
gherkin_official-38.0.0.dist-info/METADATA
gherkin_official-38.0.0.dist-info/RECORD
